serialobj/__init__.py
serialobj-0.8.1.dist-info/DESCRIPTION.rst
serialobj-0.8.1.dist-info/METADATA
serialobj-0.8.1.dist-info/RECORD
serialobj-0.8.1.dist-info/WHEEL
serialobj-0.8.1.dist-info/metadata.json
serialobj-0.8.1.dist-info/top_level.txt
